pydocstring/__init__.py
pydocstring/cli.py
pydocstring/exc.py
pydocstring/formatters/__init__.py
pydocstring/formatters/format_utils.py
pydocstring/formatters/google.py
pydocstring/formatters/numpy.py
pydocstring/formatters/reST.py
pydocstring-0.2.1.dist-info/LICENSE
pydocstring-0.2.1.dist-info/METADATA
pydocstring-0.2.1.dist-info/WHEEL
pydocstring-0.2.1.dist-info/entry_points.txt
pydocstring-0.2.1.dist-info/top_level.txt
pydocstring-0.2.1.dist-info/RECORD
