Metadata-Version: 2.1
Name: pydocstring
Version: 0.2.1
Summary: Package providing autocompletion capabilities for python docstrings
Home-page: https://github.com/robodair/pydocstring
Author: Alisdair Robertson
Author-email: alisdair.w.robertson@gmail.com
License: MIT
Platform: UNKNOWN
Classifier: Development Status :: 4 - Beta
Classifier: Environment :: Console
Classifier: Environment :: Plugins
Classifier: Environment :: Win32 (MS Windows)
Classifier: Intended Audience :: Developers
Classifier: License :: OSI Approved :: MIT License
Classifier: Programming Language :: Python :: 3.5
Classifier: Programming Language :: Python :: 3.6
Classifier: Programming Language :: Python :: 3.7
Classifier: Programming Language :: Python :: 3.8
Classifier: Topic :: Software Development :: Documentation
Requires-Dist: parso (>=0.1.1)
